independentreserve/__init__.py
independentreserve/authentication.py
independentreserve/exceptions.py
independentreserve/private.py
independentreserve/public.py
independentreserve/websocket.py
pyindependentreserve-0.4.1.dist-info/LICENSE
pyindependentreserve-0.4.1.dist-info/METADATA
pyindependentreserve-0.4.1.dist-info/WHEEL
pyindependentreserve-0.4.1.dist-info/top_level.txt
pyindependentreserve-0.4.1.dist-info/zip-safe
pyindependentreserve-0.4.1.dist-info/RECORD
