Metadata-Version: 2.1
Name: pyindependentreserve
Version: 0.4.1
Summary: Python client for Interacting with Independent Reserve API - The Bitcoin and Digital Currency Market
Home-page: https://github.com/MelchiSalins/pyindependentreserve
Author: Melchi Salins
Author-email: melchisalins@gmail.com
License: MIT
Keywords: Bitcoin BlockChain Crypto-currency
Classifier: Development Status :: 3 - Alpha
Classifier: License :: OSI Approved :: MIT License
Classifier: Programming Language :: Python :: 3.6
License-File: LICENSE
Requires-Dist: requests >=2.22.0
Requires-Dist: websockets ==9.1
